zimport/__init__.py
zimport/main.py
zimport/main_impl.py
zimport/pathfinder.py
zimport/pathfinder_impl.py
zimport/setup.py
zimport/util/bootstrap.py
zimport/util/cache.py
zimport/util/compile.py
zimport/util/module.py
zimport/util/path.py
zimport/util/times.py
zimport/util/tree.py
zimport/util/zip.py
zimport-0.1.10.dist-info/licenses/LICENSE
zimport-0.1.10.dist-info/METADATA
zimport-0.1.10.dist-info/WHEEL
zimport-0.1.10.dist-info/top_level.txt
zimport-0.1.10.dist-info/RECORD
