Metadata-Version: 2.4
Name: zimport
Version: 0.1.10
Summary: zimport is used to load and manage python packages from zip-archives.
Home-page: https://github.com/waveware4ai/zimport
Author: 14mhz
Author-email: 14mhz@hanmail.net
License: Apache-2.0 license
Keywords: python import package zip pyd
Requires-Python: >=3.8
License-File: LICENSE
Dynamic: author
Dynamic: author-email
Dynamic: description
Dynamic: description-content-type
Dynamic: home-page
Dynamic: keywords
Dynamic: license
Dynamic: license-file
Dynamic: requires-python
Dynamic: summary
